{"1":{"id":"1","base":3000},"2":{"id":"2","base":3000},"3":{"id":"3","base":3000},"4":{"id":"4","base":3000},"5":{"id":"5","base":3200},"6":{"id":"6","base":3200},"7":{"id":"7","base":3200},"8":{"id":"8","base":3200},"9":{"id":"9","base":3200},"10":{"id":"10","base":3400},"11":{"id":"11","base":3400},"12":{"id":"12","base":3400},"13":{"id":"13","base":3400},"14":{"id":"14","base":3400},"15":{"id":"15","base":3600},"16":{"id":"16","base":3600},"17":{"id":"17","base":3600},"18":{"id":"18","base":3600},"19":{"id":"19","base":3600},"20":{"id":"20","base":3800},"21":{"id":"21","base":3800},"22":{"id":"22","base":3800},"23":{"id":"23","base":3800},"24":{"id":"24","base":3800},"25":{"id":"25","base":4000},"26":{"id":"26","base":4000},"27":{"id":"27","base":4000},"28":{"id":"28","base":4000},"29":{"id":"29","base":4000},"30":{"id":"30","base":4200},"31":{"id":"31","base":4200},"32":{"id":"32","base":4200},"33":{"id":"33","base":4200},"34":{"id":"34","base":4200},"35":{"id":"35","base":4400},"36":{"id":"36","base":4400},"37":{"id":"37","base":4400},"38":{"id":"38","base":4400},"39":{"id":"39","base":4400},"40":{"id":"40","base":4600},"41":{"id":"41","base":4600},"42":{"id":"42","base":4600},"43":{"id":"43","base":4600},"44":{"id":"44","base":4600},"45":{"id":"45","base":4800},"46":{"id":"46","base":4800},"47":{"id":"47","base":4800},"48":{"id":"48","base":4800},"49":{"id":"49","base":4800},"50":{"id":"50","base":5000},"51":{"id":"51","base":5000},"52":{"id":"52","base":5000},"53":{"id":"53","base":5000},"54":{"id":"54","base":5000},"55":{"id":"55","base":5200},"56":{"id":"56","base":5200},"57":{"id":"57","base":5200},"58":{"id":"58","base":5200},"59":{"id":"59","base":5200},"60":{"id":"60","base":5400},"61":{"id":"61","base":5400},"62":{"id":"62","base":5400},"63":{"id":"63","base":5400},"64":{"id":"64","base":5400},"65":{"id":"65","base":5600},"66":{"id":"66","base":5600},"67":{"id":"67","base":5600},"68":{"id":"68","base":5600},"69":{"id":"69","base":5600},"70":{"id":"70","base":5800},"71":{"id":"71","base":5800},"72":{"id":"72","base":5800},"73":{"id":"73","base":5800},"74":{"id":"74","base":5800},"75":{"id":"75","base":6000},"76":{"id":"76","base":6000},"77":{"id":"77","base":6000},"78":{"id":"78","base":6000},"79":{"id":"79","base":6000},"80":{"id":"80","base":6200},"81":{"id":"81","base":6200},"82":{"id":"82","base":6200},"83":{"id":"83","base":6200},"84":{"id":"84","base":6200},"85":{"id":"85","base":6400},"86":{"id":"86","base":6400},"87":{"id":"87","base":6400},"88":{"id":"88","base":6400},"89":{"id":"89","base":6400},"90":{"id":"90","base":6600},"91":{"id":"91","base":6600},"92":{"id":"92","base":6600},"93":{"id":"93","base":6600},"94":{"id":"94","base":6600},"95":{"id":"95","base":6800},"96":{"id":"96","base":6800},"97":{"id":"97","base":6800},"98":{"id":"98","base":6800},"99":{"id":"99","base":6800},"100":{"id":"100","base":7000}}